README.txt
setup.py
minervashadow/__init__.py
minervashadow/__main__.py
minervashadow/minerva.py
minervashadow/writer.py
minervashadow.egg-info/PKG-INFO
minervashadow.egg-info/SOURCES.txt
minervashadow.egg-info/dependency_links.txt
minervashadow.egg-info/entry_points.txt
minervashadow.egg-info/requires.txt
minervashadow.egg-info/top_level.txt
minervashadow/reader/__init__.py
minervashadow/reader/course.py
minervashadow/reader/identify.py
minervashadow/reader/login.py
minervashadow/reader/reader.py
minervashadow/reader/transcript.py
minervashadow/ui/__init__.py
minervashadow/ui/cli.py
minervashadow/utils/__init__.py
minervashadow/utils/calendar.py
minervashadow/utils/exceptions.py
minervashadow/utils/package.py
minervashadow/utils/structures.py