Metadata-Version: 1.1
Name: minervashadow
Version: 0.0.4a3
Summary: A python interface to the aging minerva website.
Home-page: https://github.com/cadesalaberry/minervashadow
Author: cadesalaberry
Author-email: cadesalaberry@yahoo.com
License: UNKNOWN
Platform: UNKNOWN
Classifier: Development Status :: 3 - Alpha
Classifier: Intended Audience :: Developers
Classifier: Natural Language :: French
Classifier: License :: OSI Approved :: MIT License
Classifier: Programming Language :: Python
Classifier: Programming Language :: Python :: 2.6
